odoo/addons/pos_order_picking_link/README.rst
odoo/addons/pos_order_picking_link/__init__.py
odoo/addons/pos_order_picking_link/__manifest__.py
odoo/addons/pos_order_picking_link/i18n/pos_order_picking_link.pot
odoo/addons/pos_order_picking_link/models/__init__.py
odoo/addons/pos_order_picking_link/models/stock_picking.py
odoo/addons/pos_order_picking_link/readme/CONTRIBUTORS.rst
odoo/addons/pos_order_picking_link/readme/CREDITS.rst
odoo/addons/pos_order_picking_link/readme/DESCRIPTION.rst
odoo/addons/pos_order_picking_link/readme/USAGE.rst
odoo/addons/pos_order_picking_link/static/description/icon.png
odoo/addons/pos_order_picking_link/static/description/index.html
odoo/addons/pos_order_picking_link/views/stock_view.xml
odoo12_addon_pos_order_picking_link-12.0.1.0.1.dist-info/METADATA
odoo12_addon_pos_order_picking_link-12.0.1.0.1.dist-info/WHEEL
odoo12_addon_pos_order_picking_link-12.0.1.0.1.dist-info/top_level.txt
odoo12_addon_pos_order_picking_link-12.0.1.0.1.dist-info/RECORD
